{
    "rapid.title": "MMIT",
    "rapid.republic_of_mozambique": "REPUBLIC OF MOZAMBIQUE",
    "rapid.ministry_of_health": "MINISTRY OF HEALTH",
    "rapid.central_medicines_and_medical_articles": "CENTRAL MEDICINES AND MEDICAL ARTICLES",
    "rapid.rapid_test_title": "MMIT - MONTHLY INFORMATION MAP OF RAPID TEST",
    "rapid.month": "Month",
    "rapid.health_facility": "Health Facility",
    "rapid.year": "Year",
    "rapid.district": "District",
    "rapid.province": "Province",
    "rapid.sencond_title": "Rapid Test Balance at the health facility",
    "rapid.attentionkits": "(atention reported in test Kits)",
    "rapid.code_and_product": "Code & Product",
    "rapid.initial_stock": "Initial Stock",
    "rapid.entries": "Entries",
    "rapid.issues": "Issues",
    "rapid.loss_and_adjustment": "Loss And Adjustment",
    "rapid.inverntory": "Inverntory",
    "rapid.expiry_date": "Expiry Date",
    "rapid.third_title": "Test consumption justification",
    "rapid.third_attentiontests": "(atention reported in test units)",
    "rapid.services": "Services",
    "rapid.hiv_determine": "HIV Determine",
    "rapid.hiv_unigold": "HIV Unigold",
    "rapid.syphillis": "Syphillis",
    "rapid.malaria": "Malaria",
    "rapid.duo_teste_hiv_sifilis": "Duo-Teste HIV-sifilis",
    "rapid.hepatite_B_testes": "Hepatite B testes",
    "rapid.tdr_oral_de_hiv": "TDR Oral de HIV",
    "rapid.novo_teste": "Novo teste",
    "rapid.consumption": "Consumption",
    "rapid.positive": "Positive",
    "rapid.unjustifiled": "Unjustifiled",
    "rapid.positivo_hiv": "Positivo HIV",
    "rapid.positivo_sifilis": "Positivo Sifilis",
    "rapid.total": "Total",
    "rapid.APEs": "APEs",
    "rapid.observations": "Observations",
    "rapid.completedBy": "Completed by",
    "rapid.approvedBy": "Approved by" ,
    "rapid.dateOfCreate": "Date of creation",
    "rapid.downloadPdf": "Download PDF",
    "rapid.downloadSimam": "Download SIMAM"
}
